CONTRIBUTING.md
MANIFEST.in
README.rst
setup.py
docs/HISTORY.txt
docs/LICENSE.GPL
docs/LICENSE.txt
eea/__init__.py
eea.api.taxonomy.egg-info/PKG-INFO
eea.api.taxonomy.egg-info/SOURCES.txt
eea.api.taxonomy.egg-info/dependency_links.txt
eea.api.taxonomy.egg-info/entry_points.txt
eea.api.taxonomy.egg-info/namespace_packages.txt
eea.api.taxonomy.egg-info/not-zip-safe
eea.api.taxonomy.egg-info/requires.txt
eea.api.taxonomy.egg-info/top_level.txt
eea/api/__init__.py
eea/api/taxonomy/.~c9_invoke_73IMIT.py
eea/api/taxonomy/README.txt
eea/api/taxonomy/__init__.py
eea/api/taxonomy/configure.zcml
eea/api/taxonomy/interfaces.py
eea/api/taxonomy/patches.py
eea/api/taxonomy/patches.zcml
eea/api/taxonomy/profiles.zcml
eea/api/taxonomy/setuphandlers.py
eea/api/taxonomy/version.txt
eea/api/taxonomy/browser/__init__.py
eea/api/taxonomy/browser/configure.zcml
eea/api/taxonomy/locales/__init__.py
eea/api/taxonomy/locales/eea.pot
eea/api/taxonomy/locales/plone-manual.pot
eea/api/taxonomy/locales/update.sh
eea/api/taxonomy/locales/bg/LC_MESSAGES/eea.po
eea/api/taxonomy/locales/bg/LC_MESSAGES/plone.po
eea/api/taxonomy/locales/cs/LC_MESSAGES/eea.po
eea/api/taxonomy/locales/cs/LC_MESSAGES/plone.po
eea/api/taxonomy/locales/da/LC_MESSAGES/eea.po
eea/api/taxonomy/locales/da/LC_MESSAGES/plone.po
eea/api/taxonomy/locales/de/LC_MESSAGES/eea.po
eea/api/taxonomy/locales/de/LC_MESSAGES/plone.po
eea/api/taxonomy/locales/el/LC_MESSAGES/eea.po
eea/api/taxonomy/locales/el/LC_MESSAGES/plone.po
eea/api/taxonomy/locales/en/LC_MESSAGES/eea.po
eea/api/taxonomy/locales/en/LC_MESSAGES/plone.po
eea/api/taxonomy/locales/es/LC_MESSAGES/eea.po
eea/api/taxonomy/locales/es/LC_MESSAGES/plone.po
eea/api/taxonomy/locales/et/LC_MESSAGES/eea.po
eea/api/taxonomy/locales/et/LC_MESSAGES/plone.po
eea/api/taxonomy/locales/eu/LC_MESSAGES/eea.po
eea/api/taxonomy/locales/eu/LC_MESSAGES/plone.po
eea/api/taxonomy/locales/fi/LC_MESSAGES/eea.po
eea/api/taxonomy/locales/fi/LC_MESSAGES/plone.po
eea/api/taxonomy/locales/fr/LC_MESSAGES/eea.po
eea/api/taxonomy/locales/fr/LC_MESSAGES/plone.po
eea/api/taxonomy/locales/hr/LC_MESSAGES/eea.po
eea/api/taxonomy/locales/hr/LC_MESSAGES/plone.po
eea/api/taxonomy/locales/hu/LC_MESSAGES/eea.po
eea/api/taxonomy/locales/hu/LC_MESSAGES/plone.po
eea/api/taxonomy/locales/is/LC_MESSAGES/eea.po
